[
    {
       "column0": "James",
       "column1": "504-621-8927",
       "column2": "jbutt@gmail.com"
    },
    {
       "column0": "Josephine",
       "column1": "810-292-9388",
       "column2": "josephine_darakjy@darakjy.org"
    },
    {
       "column0": "Art",
       "column1": "856-636-8749",
       "column2": "art@venere.org"
    },
    {
       "column0": "Lenna",
       "column1": "907-385-4412",
       "column2": "lpaprocki@hotmail.com"
    },
    {
       "column0": "Donette",
       "column1": "513-570-1893",
       "column2": "donette.foller@cox.net"
    },
    {
       "column0": "Simona",
       "column1": "419-503-2484",
       "column2": "simona@morasca.com"
    },
    {
       "column0": "Mitsue",
       "column1": "773-573-6914",
       "column2": "mitsue_tollner@yahoo.com"
    },
    {
       "column0": "Leota",
       "column1": "408-752-3500",
       "column2": "leota@hotmail.com"
    },
    {
       "column0": "Sage",
       "column1": "605-414-2147",
       "column2": "sage_wieser@cox.net"
    },
    {
       "column0": "Kris",
       "column1": "410-655-8723",
       "column2": "kris@gmail.com"
    },
    {
       "column0": "Minna",
       "column1": "215-874-1229",
       "column2": "minna_amigon@yahoo.com"
    },
    {
       "column0": "Abel",
       "column1": "631-335-3414",
       "column2": "amaclead@gmail.com"
    },
    {
       "column0": "Kiley",
       "column1": "310-498-5651",
       "column2": "kiley.caldarera@aol.com"
    },
    {
       "column0": "Graciela",
       "column1": "440-780-8425",
       "column2": "gruta@cox.net"
    },
    {
       "column0": "Cammy",
       "column1": "956-537-6195",
       "column2": "calbares@gmail.com"
    },
    {
       "column0": "Mattie",
       "column1": "602-277-4385",
       "column2": "mattie@aol.com"
    },
    {
       "column0": "Meaghan",
       "column1": "931-313-9635",
       "column2": "meaghan@hotmail.com"
    },
    {
       "column0": "Gladys",
       "column1": "414-661-9598",
       "column2": "gladys.rim@rim.org"
    },
    {
       "column0": "Yuki",
       "column1": "313-288-7937",
       "column2": "yuki_whobrey@aol.com"
    },
    {
       "column0": "Fletcher",
       "column1": "815-828-2147",
       "column2": "fletcher.flosi@yahoo.com"
    },
    {
       "column0": "Bette",
       "column1": "610-545-3615",
       "column2": "bette_nicka@cox.net"
    },
    {
       "column0": "Veronika",
       "column1": "408-540-1785",
       "column2": "vinouye@aol.com"
    },
    {
       "column0": "Willard",
       "column1": "972-303-9197",
       "column2": "willard@hotmail.com"
    },
    {
       "column0": "Maryann",
       "column1": "518-966-7987",
       "column2": "mroyster@royster.com"
    },
    {
       "column0": "Alisha",
       "column1": "732-658-3154",
       "column2": "alisha@slusarski.com"
    },
    {
       "column0": "Allene",
       "column1": "715-662-6764",
       "column2": "allene_iturbide@cox.net"
    },
    {
       "column0": "Chanel",
       "column1": "913-388-2079",
       "column2": "chanel.caudy@caudy.org"
    },
    {
       "column0": "Ezekiel",
       "column1": "410-669-1642",
       "column2": "ezekiel@chui.com"
    },
    {
       "column0": "Manuel",
       "column1": "123",
       "column2": "feelmaneco@gmail.com"
    },
    {
       "column0": "Bernardo",
       "column1": "936-336-3951",
       "column2": "bfigeroa@aol.com"
    },
    {
       "column0": "Ammie",
       "column1": "614-801-9788",
       "column2": "ammie@corrio.com"
    },
    {
       "column0": "Francine",
       "column1": "505-977-3911",
       "column2": "francine_vocelka@vocelka.com"
    },
    {
       "column0": "Ernie",
       "column1": "201-709-6245",
       "column2": "ernie_stenseth@aol.com"
    },
    {
       "column0": "Albina",
       "column1": "732-924-7882",
       "column2": "albina@glick.com"
    },
    {
       "column0": "Alishia",
       "column1": "212-860-1579",
       "column2": "asergi@gmail.com"
    },
    {
       "column0": "Solange",
       "column1": "504-979-9175",
       "column2": "solange@shinko.com"
    },
    {
       "column0": "Jose",
       "column1": "212-675-8570",
       "column2": "jose@yahoo.com"
    },
    {
       "column0": "Rozella",
       "column1": "805-832-6163",
       "column2": "rozella.ostrosky@ostrosky.com"
    },
    {
       "column0": "Valentine",
       "column1": "210-812-9597",
       "column2": "valentine_gillian@gmail.com"
    },
    {
       "column0": "Kati",
       "column1": "785-463-7829",
       "column2": "kati.rulapaugh@hotmail.com"
    },
    {
       "column0": "Youlanda",
       "column1": "541-548-8197",
       "column2": "youlanda@aol.com"
    },
    {
       "column0": "Dyan",
       "column1": "913-413-4604",
       "column2": "doldroyd@aol.com"
    },
    {
       "column0": "Roxane",
       "column1": "907-231-4722",
       "column2": "roxane@hotmail.com"
    },
    {
       "column0": "Lavera",
       "column1": "305-606-7291",
       "column2": "lperin@perin.org"
    },
    {
       "column0": "Erick",
       "column1": "907-741-1044",
       "column2": "erick.ferencz@aol.com"
    },
    {
       "column0": "Fatima",
       "column1": "952-768-2416",
       "column2": "fsaylors@saylors.org"
    },
    {
       "column0": "Jina",
       "column1": "617-399-5124",
       "column2": "jina_briddick@briddick.com"
    },
    {
       "column0": "Kanisha",
       "column1": "323-453-2780",
       "column2": "kanisha_waycott@yahoo.com"
    },
    {
       "column0": "Emerson",
       "column1": "608-336-7444",
       "column2": "emerson.bowley@bowley.org"
    },
    {
       "column0": "Blair",
       "column1": "215-907-9111",
       "column2": "bmalet@yahoo.com"
    },
    {
       "column0": "Brock",
       "column1": "212-402-9216",
       "column2": "bbolognia@yahoo.com"
    },
    {
       "column0": "Lorrie",
       "column1": "931-875-6644",
       "column2": "lnestle@hotmail.com"
    },
    {
       "column0": "Sabra",
       "column1": "803-925-5213",
       "column2": "sabra@uyetake.org"
    },
    {
       "column0": "Marjory",
       "column1": "610-814-5533",
       "column2": "mmastella@mastella.com"
    },
    {
       "column0": "Karl",
       "column1": "908-877-6135",
       "column2": "karl_klonowski@yahoo.com"
    },
    {
       "column0": "Tonette",
       "column1": "516-968-6051",
       "column2": "twenner@aol.com"
    },
    {
       "column0": "Amber",
       "column1": "215-934-8655",
       "column2": "amber_monarrez@monarrez.org"
    },
    {
       "column0": "Shenika",
       "column1": "818-423-4007",
       "column2": "shenika@gmail.com"
    },
    {
       "column0": "Delmy",
       "column1": "401-458-2547",
       "column2": "delmy.ahle@hotmail.com"
    },
    {
       "column0": "Deeanna",
       "column1": "215-211-9589",
       "column2": "deeanna_juhas@gmail.com"
    },
    {
       "column0": "Blondell",
       "column1": "401-960-8259",
       "column2": "bpugh@aol.com"
    },
    {
       "column0": "Jamal",
       "column1": "732-234-1546",
       "column2": "jamal@vanausdal.org"
    },
    {
       "column0": "Cecily",
       "column1": "512-486-3817",
       "column2": "cecily@hollack.org"
    },
    {
       "column0": "Carmelina",
       "column1": "303-724-7371",
       "column2": "carmelina_lindall@lindall.com"
    },
    {
       "column0": "Maurine",
       "column1": "414-748-1374",
       "column2": "maurine_yglesias@yglesias.com"
    },
    {
       "column0": "Tawna",
       "column1": "212-674-9610",
       "column2": "tawna@gmail.com"
    },
    {
       "column0": "Penney",
       "column1": "907-797-9628",
       "column2": "penney_weight@aol.com"
    },
    {
       "column0": "Elly",
       "column1": "814-393-5571",
       "column2": "elly_morocco@gmail.com"
    },
    {
       "column0": "Ilene",
       "column1": "410-914-9018",
       "column2": "ilene.eroman@hotmail.com"
    },
    {
       "column0": "Vallie",
       "column1": "208-862-5339",
       "column2": "vmondella@mondella.com"
    },
    {
       "column0": "Kallie",
       "column1": "415-315-2761",
       "column2": "kallie.blackwood@gmail.com"
    },
    {
       "column0": "Johnetta",
       "column1": "919-225-9345",
       "column2": "johnetta_abdallah@aol.com"
    },
    {
       "column0": "Bobbye",
       "column1": "650-528-5783",
       "column2": "brhym@rhym.com"
    },
    {
       "column0": "Micaela",
       "column1": "925-647-3298",
       "column2": "micaela_rhymes@gmail.com"
    },
    {
       "column0": "Tamar",
       "column1": "740-343-8575",
       "column2": "tamar@hotmail.com"
    },
    {
       "column0": "Moon",
       "column1": "585-866-8313",
       "column2": "moon@yahoo.com"
    },
    {
       "column0": "Laurel",
       "column1": "410-520-4832",
       "column2": "laurel_reitler@reitler.com"
    },
    {
       "column0": "Delisa",
       "column1": "973-354-2040",
       "column2": "delisa.crupi@crupi.com"
    },
    {
       "column0": "Viva",
       "column1": "773-446-5569",
       "column2": "viva.toelkes@gmail.com"
    },
    {
       "column0": "Elza",
       "column1": "973-927-3447",
       "column2": "elza@yahoo.com"
    },
    {
       "column0": "Devorah",
       "column1": "505-975-8559",
       "column2": "devorah@hotmail.com"
    },
    {
       "column0": "Timothy",
       "column1": "718-332-6527",
       "column2": "timothy_mulqueen@mulqueen.org"
    },
    {
       "column0": "Arlette",
       "column1": "904-775-4480",
       "column2": "ahoneywell@honeywell.com"
    },
    {
       "column0": "Dominque",
       "column1": "510-993-3758",
       "column2": "dominque.dickerson@dickerson.org"
    },
    {
       "column0": "Lettie",
       "column1": "216-657-7668",
       "column2": "lettie_isenhower@yahoo.com"
    },
    {
       "column0": "Myra",
       "column1": "817-914-7518",
       "column2": "mmunns@cox.net"
    },
    {
       "column0": "Stephaine",
       "column1": "310-774-7643",
       "column2": "stephaine@barfield.com"
    },
    {
       "column0": "Lai",
       "column1": "847-728-7286",
       "column2": "lai.gato@gato.org"
    },
    {
       "column0": "Stephen",
       "column1": "330-537-5358",
       "column2": "stephen_emigh@hotmail.com"
    },
    {
       "column0": "Tyra",
       "column1": "215-255-1641",
       "column2": "tshields@gmail.com"
    },
    {
       "column0": "Tammara",
       "column1": "650-803-1936",
       "column2": "twardrip@cox.net"
    },
    {
       "column0": "Cory",
       "column1": "626-572-1096",
       "column2": "cory.gibes@gmail.com"
    },
    {
       "column0": "Danica",
       "column1": "254-782-8569",
       "column2": "danica_bruschke@gmail.com"
    },
    {
       "column0": "Wilda",
       "column1": "907-870-5536",
       "column2": "wilda@cox.net"
    },
    {
       "column0": "Elvera",
       "column1": "408-703-8505",
       "column2": "elvera.benimadho@cox.net"
    },
    {
       "column0": "Carma",
       "column1": "510-503-7169",
       "column2": "carma@cox.net"
    },
    {
       "column0": "Malinda",
       "column1": "317-722-5066",
       "column2": "malinda.hochard@yahoo.com"
    },
    {
       "column0": "Natalie",
       "column1": "307-704-8713",
       "column2": "natalie.fern@hotmail.com"
    },
    {
       "column0": "Lisha",
       "column1": "703-235-3937",
       "column2": "lisha@centini.org"
    },
    {
       "column0": "Arlene",
       "column1": "504-710-5840",
       "column2": "arlene_klusman@gmail.com"
    },
    {
       "column0": "Alease",
       "column1": "303-301-4946",
       "column2": "alease@buemi.com"
    },
    {
       "column0": "Louisa",
       "column1": "510-828-7047",
       "column2": "louisa@cronauer.com"
    },
    {
       "column0": "Angella",
       "column1": "808-892-7943",
       "column2": "angella.cetta@hotmail.com"
    },
    {
       "column0": "Cyndy",
       "column1": "952-334-9408",
       "column2": "cgoldammer@cox.net"
    },
    {
       "column0": "Rosio",
       "column1": "336-243-5659",
       "column2": "rosio.cork@gmail.com"
    },
    {
       "column0": "Celeste",
       "column1": "516-509-2347",
       "column2": "ckorando@hotmail.com"
    },
    {
       "column0": "Twana",
       "column1": "503-939-3153",
       "column2": "twana.felger@felger.org"
    },
    {
       "column0": "Estrella",
       "column1": "608-976-7199",
       "column2": "estrella@aol.com"
    },
    {
       "column0": "Donte",
       "column1": "508-429-8576",
       "column2": "dkines@hotmail.com"
    },
    {
       "column0": "Tiffiny",
       "column1": "305-385-9695",
       "column2": "tiffiny_steffensmeier@cox.net"
    },
    {
       "column0": "Edna",
       "column1": "814-460-2655",
       "column2": "emiceli@miceli.org"
    },
    {
       "column0": "Sue",
       "column1": "972-666-3413",
       "column2": "sue@aol.com"
    },
    {
       "column0": "Jesusa",
       "column1": "931-273-8709",
       "column2": "jshin@shin.com"
    },
    {
       "column0": "Rolland",
       "column1": "973-649-2922",
       "column2": "rolland@cox.net"
    },
    {
       "column0": "Pamella",
       "column1": "305-420-8970",
       "column2": "pamella.schmierer@schmierer.org"
    },
    {
       "column0": "Glory",
       "column1": "410-224-9462",
       "column2": "gkulzer@kulzer.org"
    },
    {
       "column0": "Shawna",
       "column1": "805-275-3566",
       "column2": "shawna_palaspas@palaspas.org"
    },
    {
       "column0": "Brandon",
       "column1": "808-215-6832",
       "column2": "brandon_callaro@hotmail.com"
    },
    {
       "column0": "Scarlet",
       "column1": "229-735-3378",
       "column2": "scarlet.cartan@yahoo.com"
    },
    {
       "column0": "Oretha",
       "column1": "617-418-5043",
       "column2": "oretha_menter@yahoo.com"
    },
    {
       "column0": "Ty",
       "column1": "201-672-1553",
       "column2": "tsmith@aol.com"
    },
    {
       "column0": "Xuan",
       "column1": "650-933-5072",
       "column2": "xuan@gmail.com"
    },
    {
       "column0": "Lindsey",
       "column1": "909-639-9887",
       "column2": "lindsey.dilello@hotmail.com"
    },
    {
       "column0": "Devora",
       "column1": "510-955-3016",
       "column2": "devora_perez@perez.org"
    },
    {
       "column0": "Herman",
       "column1": "518-497-2940",
       "column2": "hdemesa@cox.net"
    },
    {
       "column0": "Rory",
       "column1": "570-867-7489",
       "column2": "rpapasergi@cox.net"
    },
    {
       "column0": "Talia",
       "column1": "973-245-2133",
       "column2": "talia_riopelle@aol.com"
    },
    {
       "column0": "Van",
       "column1": "908-409-2890",
       "column2": "van.shire@shire.com"
    },
    {
       "column0": "Lucina",
       "column1": "321-749-4981",
       "column2": "lucina_lary@cox.net"
    },
    {
       "column0": "Bok",
       "column1": "718-809-3762",
       "column2": "bok.isaacs@aol.com"
    },
    {
       "column0": "Rolande",
       "column1": "808-315-3077",
       "column2": "rolande.spickerman@spickerman.com"
    },
    {
       "column0": "Howard",
       "column1": "303-623-4241",
       "column2": "hpaulas@gmail.com"
    },
    {
       "column0": "Kimbery",
       "column1": "973-310-1634",
       "column2": "kimbery_madarang@cox.net"
    },
    {
       "column0": "Thurman",
       "column1": "609-524-3586",
       "column2": "thurman.manno@yahoo.com"
    },
    {
       "column0": "Becky",
       "column1": "908-877-8409",
       "column2": "becky.mirafuentes@mirafuentes.com"
    },
    {
       "column0": "Beatriz",
       "column1": "508-584-4279",
       "column2": "beatriz@yahoo.com"
    },
    {
       "column0": "Marti",
       "column1": "773-775-4522",
       "column2": "marti.maybury@yahoo.com"
    },
    {
       "column0": "Nieves",
       "column1": "503-527-5274",
       "column2": "nieves_gotter@gmail.com"
    },
    {
       "column0": "Leatha",
       "column1": "214-339-1809",
       "column2": "lhagele@cox.net"
    },
    {
       "column0": "Valentin",
       "column1": "312-303-5453",
       "column2": "vklimek@klimek.org"
    },
    {
       "column0": "Melissa",
       "column1": "419-939-3613",
       "column2": "melissa@cox.net"
    },
    {
       "column0": "Sheridan",
       "column1": "951-645-3605",
       "column2": "sheridan.zane@zane.com"
    },
    {
       "column0": "Bulah",
       "column1": "254-463-4368",
       "column2": "bulah_padilla@hotmail.com"
    },
    {
       "column0": "Audra",
       "column1": "615-406-7854",
       "column2": "audra@kohnert.com"
    },
    {
       "column0": "Daren",
       "column1": "414-959-2540",
       "column2": "dweirather@aol.com"
    },
    {
       "column0": "Fernanda",
       "column1": "410-387-5260",
       "column2": "fjillson@aol.com"
    },
    {
       "column0": "Gearldine",
       "column1": "972-934-6914",
       "column2": "gearldine_gellinger@gellinger.com"
    },
    {
       "column0": "Chau",
       "column1": "310-560-8022",
       "column2": "chau@gmail.com"
    },
    {
       "column0": "Theola",
       "column1": "516-948-5768",
       "column2": "theola_frey@frey.com"
    },
    {
       "column0": "Cheryl",
       "column1": "609-518-7697",
       "column2": "cheryl@haroldson.org"
    },
    {
       "column0": "Laticia",
       "column1": "513-508-7371",
       "column2": "lmerced@gmail.com"
    },
    {
       "column0": "Carissa",
       "column1": "541-326-4074",
       "column2": "carissa.batman@yahoo.com"
    },
    {
       "column0": "Lezlie",
       "column1": "919-533-3762",
       "column2": "lezlie.craghead@craghead.org"
    },
    {
       "column0": "Ozell",
       "column1": "212-332-8435",
       "column2": "oshealy@hotmail.com"
    },
    {
       "column0": "Arminda",
       "column1": "602-906-9419",
       "column2": "arminda@parvis.com"
    },
    {
       "column0": "Reita",
       "column1": "317-234-1135",
       "column2": "reita.leto@gmail.com"
    },
    {
       "column0": "Yolando",
       "column1": "315-304-4759",
       "column2": "yolando@cox.net"
    },
    {
       "column0": "Lizette",
       "column1": "856-487-5412",
       "column2": "lizette.stem@aol.com"
    },
    {
       "column0": "Gregoria",
       "column1": "516-212-1915",
       "column2": "gpawlowicz@yahoo.com"
    },
    {
       "column0": "Carin",
       "column1": "501-308-1040",
       "column2": "cdeleo@deleo.com"
    },
    {
       "column0": "Chantell",
       "column1": "651-591-2583",
       "column2": "chantell@yahoo.com"
    },
    {
       "column0": "Dierdre",
       "column1": "215-325-3042",
       "column2": "dyum@yahoo.com"
    },
    {
       "column0": "Larae",
       "column1": "985-890-7262",
       "column2": "larae_gudroe@gmail.com"
    },
    {
       "column0": "Latrice",
       "column1": "631-957-7624",
       "column2": "latrice.tolfree@hotmail.com"
    },
    {
       "column0": "Kerry",
       "column1": "916-591-3277",
       "column2": "kerry.theodorov@gmail.com"
    },
    {
       "column0": "Dorthy",
       "column1": "208-649-2373",
       "column2": "dhidvegi@yahoo.com"
    },
    {
       "column0": "Fannie",
       "column1": "512-587-5746",
       "column2": "fannie.lungren@yahoo.com"
    },
    {
       "column0": "Evangelina",
       "column1": "215-964-3284",
       "column2": "evangelina@aol.com"
    },
    {
       "column0": "Novella",
       "column1": "808-477-4775",
       "column2": "novella_degroot@degroot.org"
    },
    {
       "column0": "Clay",
       "column1": "775-501-8109",
       "column2": "choa@hoa.org"
    },
    {
       "column0": "Jennifer",
       "column1": "847-979-9545",
       "column2": "jfallick@yahoo.com"
    },
    {
       "column0": "Irma",
       "column1": "973-545-7355",
       "column2": "irma.wolfgramm@hotmail.com"
    },
    {
       "column0": "Eun",
       "column1": "864-256-3620",
       "column2": "eun@yahoo.com"
    },
    {
       "column0": "Sylvia",
       "column1": "410-209-9545",
       "column2": "sylvia_cousey@cousey.org"
    },
    {
       "column0": "Nana",
       "column1": "914-855-2115",
       "column2": "nana@aol.com"
    },
    {
       "column0": "Layla",
       "column1": "212-260-3151",
       "column2": "layla.springe@cox.net"
    },
    {
       "column0": "Joesph",
       "column1": "510-677-9785",
       "column2": "joesph_degonia@degonia.org"
    },
    {
       "column0": "Annabelle",
       "column1": "978-697-6263",
       "column2": "annabelle.boord@cox.net"
    },
    {
       "column0": "Stephaine",
       "column1": "415-767-6596",
       "column2": "stephaine@cox.net"
    },
    {
       "column0": "Nelida",
       "column1": "201-971-1638",
       "column2": "nelida@gmail.com"
    },
    {
       "column0": "Marguerita",
       "column1": "925-634-7158",
       "column2": "marguerita.hiatt@gmail.com"
    },
    {
       "column0": "Carmela",
       "column1": "773-494-4195",
       "column2": "ccookey@cookey.org"
    },
    {
       "column0": "Junita",
       "column1": "973-943-3423",
       "column2": "jbrideau@aol.com"
    },
    {
       "column0": "Claribel",
       "column1": "419-544-4900",
       "column2": "claribel_varriano@cox.net"
    },
    {
       "column0": "Benton",
       "column1": "310-579-2907",
       "column2": "benton.skursky@aol.com"
    },
    {
       "column0": "Hillary",
       "column1": "352-242-2570",
       "column2": "hillary.skulski@aol.com"
    },
    {
       "column0": "Merilyn",
       "column1": "408-758-5015",
       "column2": "merilyn_bayless@cox.net"
    },
    {
       "column0": "Teri",
       "column1": "570-889-5187",
       "column2": "tennaco@gmail.com"
    },
    {
       "column0": "Merlyn",
       "column1": "201-588-7810",
       "column2": "merlyn_lawler@hotmail.com"
    },
    {
       "column0": "Georgene",
       "column1": "925-615-5185",
       "column2": "gmontezuma@cox.net"
    },
    {
       "column0": "Jettie",
       "column1": "908-802-3564",
       "column2": "jmconnell@hotmail.com"
    },
    {
       "column0": "Lemuel",
       "column1": "631-748-6479",
       "column2": "lemuel.latzke@gmail.com"
    },
    {
       "column0": "Melodie",
       "column1": "805-690-1682",
       "column2": "mknipp@gmail.com"
    },
    {
       "column0": "Candida",
       "column1": "908-275-8357",
       "column2": "candida_corbley@hotmail.com"
    },
    {
       "column0": "Karan",
       "column1": "503-940-8327",
       "column2": "karan_karpin@gmail.com"
    },
    {
       "column0": "Andra",
       "column1": "503-516-2189",
       "column2": "andra@gmail.com"
    },
    {
       "column0": "Felicidad",
       "column1": "856-305-9731",
       "column2": "fpoullion@poullion.com"
    },
    {
       "column0": "Belen",
       "column1": "770-507-8791",
       "column2": "belen_strassner@aol.com"
    },
    {
       "column0": "Gracia",
       "column1": "904-235-3633",
       "column2": "gracia@melnyk.com"
    },
    {
       "column0": "Jolanda",
       "column1": "207-458-9196",
       "column2": "jhanafan@gmail.com"
    },
    {
       "column0": "Barrett",
       "column1": "817-765-5781",
       "column2": "barrett.toyama@toyama.org"
    },
    {
       "column0": "Helga",
       "column1": "716-752-4114",
       "column2": "helga_fredicks@yahoo.com"
    },
    {
       "column0": "Ashlyn",
       "column1": "305-670-9628",
       "column2": "apinilla@cox.net"
    },
    {
       "column0": "Fausto",
       "column1": "212-313-1783",
       "column2": "fausto_agramonte@yahoo.com"
    },
    {
       "column0": "Ronny",
       "column1": "215-605-7570",
       "column2": "ronny.caiafa@caiafa.org"
    },
    {
       "column0": "Marge",
       "column1": "850-430-1663",
       "column2": "marge@gmail.com"
    },
    {
       "column0": "Norah",
       "column1": "415-306-7897",
       "column2": "norah.waymire@gmail.com"
    },
    {
       "column0": "Aliza",
       "column1": "408-504-3552",
       "column2": "aliza@aol.com"
    },
    {
       "column0": "Mozell",
       "column1": "650-947-1215",
       "column2": "mpelkowski@pelkowski.org"
    },
    {
       "column0": "Viola",
       "column1": "818-864-4875",
       "column2": "viola@gmail.com"
    },
    {
       "column0": "Franklyn",
       "column1": "215-558-8189",
       "column2": "femard@emard.com"
    },
    {
       "column0": "Willodean",
       "column1": "337-253-8384",
       "column2": "willodean_konopacki@konopacki.org"
    },
    {
       "column0": "Beckie",
       "column1": "313-533-4884",
       "column2": "beckie.silvestrini@silvestrini.com"
    },
    {
       "column0": "Rebecka",
       "column1": "512-213-8574",
       "column2": "rgesick@gesick.org"
    },
    {
       "column0": "Frederica",
       "column1": "214-428-2285",
       "column2": "frederica_blunk@gmail.com"
    },
    {
       "column0": "Glen",
       "column1": "206-697-5796",
       "column2": "glen_bartolet@hotmail.com"
    },
    {
       "column0": "Freeman",
       "column1": "610-476-3501",
       "column2": "freeman_gochal@aol.com"
    },
    {
       "column0": "Vincent",
       "column1": "215-372-1718",
       "column2": "vincent.meinerding@hotmail.com"
    },
    {
       "column0": "Rima",
       "column1": "310-858-5079",
       "column2": "rima@cox.net"
    },
    {
       "column0": "Glendora",
       "column1": "707-653-8214",
       "column2": "gsarbacher@gmail.com"
    },
    {
       "column0": "Avery",
       "column1": "407-808-9439",
       "column2": "avery@cox.net"
    },
    {
       "column0": "Cristy",
       "column1": "760-971-4322",
       "column2": "cristy@lother.com"
    },
    {
       "column0": "Nicolette",
       "column1": "508-837-9230",
       "column2": "nicolette_brossart@brossart.com"
    },
    {
       "column0": "Tracey",
       "column1": "936-264-9294",
       "column2": "tracey@hotmail.com"
    },
    {
       "column0": "Virgina",
       "column1": "414-214-8697",
       "column2": "virgina_tegarden@tegarden.com"
    },
    {
       "column0": "Tiera",
       "column1": "626-636-4117",
       "column2": "tfrankel@aol.com"
    },
    {
       "column0": "Alaine",
       "column1": "914-300-9193",
       "column2": "alaine_bergesen@cox.net"
    },
    {
       "column0": "Earleen",
       "column1": "214-289-1973",
       "column2": "earleen_mai@cox.net"
    },
    {
       "column0": "Leonida",
       "column1": "228-235-5615",
       "column2": "leonida@gobern.org"
    },
    {
       "column0": "Ressie",
       "column1": "305-604-8981",
       "column2": "ressie.auffrey@yahoo.com"
    },
    {
       "column0": "Justine",
       "column1": "212-304-9225",
       "column2": "jmugnolo@yahoo.com"
    },
    {
       "column0": "Eladia",
       "column1": "201-474-4924",
       "column2": "eladia@saulter.com"
    },
    {
       "column0": "Chaya",
       "column1": "734-928-5182",
       "column2": "chaya@malvin.com"
    },
    {
       "column0": "Gwenn",
       "column1": "631-258-6558",
       "column2": "gwenn_suffield@suffield.org"
    },
    {
       "column0": "Salena",
       "column1": "330-791-8557",
       "column2": "skarpel@cox.net"
    },
    {
       "column0": "Yoko",
       "column1": "203-506-4706",
       "column2": "yoko@fishburne.com"
    },
    {
       "column0": "Taryn",
       "column1": "703-322-4041",
       "column2": "taryn.moyd@hotmail.com"
    },
    {
       "column0": "Katina",
       "column1": "978-626-2978",
       "column2": "katina_polidori@aol.com"
    },
    {
       "column0": "Rickie",
       "column1": "419-693-1334",
       "column2": "rickie.plumer@aol.com"
    },
    {
       "column0": "Alex",
       "column1": "253-660-7821",
       "column2": "alex@loader.com"
    },
    {
       "column0": "Lashon",
       "column1": "916-741-7884",
       "column2": "lashon@aol.com"
    },
    {
       "column0": "Lauran",
       "column1": "307-342-7795",
       "column2": "lburnard@burnard.com"
    },
    {
       "column0": "Ceola",
       "column1": "207-627-7565",
       "column2": "ceola.setter@setter.org"
    },
    {
       "column0": "My",
       "column1": "215-491-5633",
       "column2": "my@hotmail.com"
    },
    {
       "column0": "Lorrine",
       "column1": "813-769-2939",
       "column2": "lorrine.worlds@worlds.com"
    },
    {
       "column0": "Peggie",
       "column1": "619-608-1763",
       "column2": "peggie@cox.net"
    },
    {
       "column0": "Marvel",
       "column1": "979-718-8968",
       "column2": "mraymo@yahoo.com"
    },
    {
       "column0": "Daron",
       "column1": "847-233-3075",
       "column2": "daron_dinos@cox.net"
    },
    {
       "column0": "An",
       "column1": "609-228-5265",
       "column2": "an_fritz@hotmail.com"
    },
    {
       "column0": "Portia",
       "column1": "908-722-7128",
       "column2": "portia.stimmel@aol.com"
    },
    {
       "column0": "Rhea",
       "column1": "718-560-9537",
       "column2": "rhea_aredondo@cox.net"
    },
    {
       "column0": "Benedict",
       "column1": "314-787-1588",
       "column2": "bsama@cox.net"
    },
    {
       "column0": "Alyce",
       "column1": "209-317-1801",
       "column2": "alyce@arias.org"
    },
    {
       "column0": "Heike",
       "column1": "973-936-5095",
       "column2": "heike@gmail.com"
    },
    {
       "column0": "Carey",
       "column1": "317-578-2453",
       "column2": "carey_dopico@dopico.org"
    },
    {
       "column0": "Dottie",
       "column1": "206-540-6076",
       "column2": "dottie@hellickson.org"
    },
    {
       "column0": "Deandrea",
       "column1": "336-822-7652",
       "column2": "deandrea@yahoo.com"
    },
    {
       "column0": "Kimberlie",
       "column1": "785-629-8542",
       "column2": "kimberlie_duenas@yahoo.com"
    },
    {
       "column0": "Martina",
       "column1": "407-471-6908",
       "column2": "martina_staback@staback.com"
    },
    {
       "column0": "Skye",
       "column1": "612-508-2655",
       "column2": "skye_fillingim@yahoo.com"
    },
    {
       "column0": "Jade",
       "column1": "803-352-5387",
       "column2": "jade.farrar@yahoo.com"
    },
    {
       "column0": "Charlene",
       "column1": "707-300-1771",
       "column2": "charlene.hamilton@hotmail.com"
    },
    {
       "column0": "Geoffrey",
       "column1": "847-222-1734",
       "column2": "geoffrey@gmail.com"
    },
    {
       "column0": "Stevie",
       "column1": "949-867-4077",
       "column2": "stevie.westerbeck@yahoo.com"
    },
    {
       "column0": "Pamella",
       "column1": "303-404-2210",
       "column2": "pamella@fortino.com"
    },
    {
       "column0": "Harrison",
       "column1": "203-801-6193",
       "column2": "hhaufler@hotmail.com"
    },
    {
       "column0": "Johnna",
       "column1": "425-986-7573",
       "column2": "jengelberg@engelberg.org"
    },
    {
       "column0": "Buddy",
       "column1": "440-989-5826",
       "column2": "buddy.cloney@yahoo.com"
    },
    {
       "column0": "Dalene",
       "column1": "603-315-6839",
       "column2": "dalene.riden@aol.com"
    },
    {
       "column0": "Jerry",
       "column1": "321-518-5938",
       "column2": "jzurcher@zurcher.org"
    },
    {
       "column0": "Haydee",
       "column1": "212-792-8658",
       "column2": "hdenooyer@denooyer.org"
    },
    {
       "column0": "Joseph",
       "column1": "714-584-2237",
       "column2": "joseph_cryer@cox.net"
    },
    {
       "column0": "Deonna",
       "column1": "248-913-4677",
       "column2": "deonna_kippley@hotmail.com"
    },
    {
       "column0": "Raymon",
       "column1": "317-825-4724",
       "column2": "raymon.calvaresi@gmail.com"
    },
    {
       "column0": "Alecia",
       "column1": "940-276-7922",
       "column2": "alecia@aol.com"
    },
    {
       "column0": "Ma",
       "column1": "203-721-3388",
       "column2": "mlayous@hotmail.com"
    },
    {
       "column0": "Detra",
       "column1": "410-739-9277",
       "column2": "detra@aol.com"
    },
    {
       "column0": "Terrilyn",
       "column1": "504-463-4384",
       "column2": "terrilyn.rodeigues@cox.net"
    },
    {
       "column0": "Salome",
       "column1": "804-550-5097",
       "column2": "slacovara@gmail.com"
    },
    {
       "column0": "Garry",
       "column1": "215-979-8776",
       "column2": "garry_keetch@hotmail.com"
    },
    {
       "column0": "Matthew",
       "column1": "952-651-7597",
       "column2": "mneither@yahoo.com"
    },
    {
       "column0": "Theodora",
       "column1": "305-936-8226",
       "column2": "theodora.restrepo@restrepo.com"
    },
    {
       "column0": "Noah",
       "column1": "414-263-5287",
       "column2": "noah.kalafatis@aol.com"
    },
    {
       "column0": "Carmen",
       "column1": "732-941-2621",
       "column2": "csweigard@sweigard.com"
    },
    {
       "column0": "Lavonda",
       "column1": "701-898-2154",
       "column2": "lavonda@cox.net"
    },
    {
       "column0": "Junita",
       "column1": "775-638-9963",
       "column2": "junita@aol.com"
    },
    {
       "column0": "Herminia",
       "column1": "602-954-5141",
       "column2": "herminia@nicolozakes.org"
    },
    {
       "column0": "Casie",
       "column1": "615-390-2251",
       "column2": "casie.good@aol.com"
    },
    {
       "column0": "Reena",
       "column1": "410-351-1863",
       "column2": "reena@hotmail.com"
    },
    {
       "column0": "Mirta",
       "column1": "212-870-1286",
       "column2": "mirta_mallett@gmail.com"
    },
    {
       "column0": "Cathrine",
       "column1": "806-703-1435",
       "column2": "cathrine.pontoriero@pontoriero.com"
    },
    {
       "column0": "Filiberto",
       "column1": "323-765-2528",
       "column2": "ftawil@hotmail.com"
    },
    {
       "column0": "Raul",
       "column1": "619-509-5282",
       "column2": "rupthegrove@yahoo.com"
    },
    {
       "column0": "Sarah",
       "column1": "770-732-1194",
       "column2": "sarah.candlish@gmail.com"
    },
    {
       "column0": "Lucy",
       "column1": "508-769-5250",
       "column2": "lucy@cox.net"
    },
    {
       "column0": "Judy",
       "column1": "269-756-7222",
       "column2": "jaquas@aquas.com"
    },
    {
       "column0": "Yvonne",
       "column1": "973-714-1721",
       "column2": "yvonne.tjepkema@hotmail.com"
    },
    {
       "column0": "Kayleigh",
       "column1": "337-740-9323",
       "column2": "kayleigh.lace@yahoo.com"
    },
    {
       "column0": "Felix",
       "column1": "717-491-5643",
       "column2": "felix_hirpara@cox.net"
    },
    {
       "column0": "Tresa",
       "column1": "314-359-9566",
       "column2": "tresa_sweely@hotmail.com"
    },
    {
       "column0": "Kristeen",
       "column1": "817-213-8851",
       "column2": "kristeen@gmail.com"
    },
    {
       "column0": "Jenelle",
       "column1": "813-932-8715",
       "column2": "jregusters@regusters.com"
    },
    {
       "column0": "Renea",
       "column1": "770-679-4752",
       "column2": "renea@hotmail.com"
    },
    {
       "column0": "Olive",
       "column1": "760-938-6069",
       "column2": "olive@aol.com"
    },
    {
       "column0": "Ligia",
       "column1": "517-906-1108",
       "column2": "lreiber@cox.net"
    },
    {
       "column0": "Christiane",
       "column1": "602-390-4944",
       "column2": "christiane.eschberger@yahoo.com"
    },
    {
       "column0": "Goldie",
       "column1": "207-295-7569",
       "column2": "goldie.schirpke@yahoo.com"
    },
    {
       "column0": "Loreta",
       "column1": "301-696-6420",
       "column2": "loreta.timenez@hotmail.com"
    },
    {
       "column0": "Fabiola",
       "column1": "717-809-3119",
       "column2": "fabiola.hauenstein@hauenstein.org"
    },
    {
       "column0": "Amie",
       "column1": "972-419-7946",
       "column2": "amie.perigo@yahoo.com"
    },
    {
       "column0": "Raina",
       "column1": "406-318-1515",
       "column2": "raina.brachle@brachle.org"
    },
    {
       "column0": "Erinn",
       "column1": "973-767-3008",
       "column2": "erinn.canlas@canlas.com"
    },
    {
       "column0": "Cherry",
       "column1": "248-980-6904",
       "column2": "cherry@lietz.com"
    },
    {
       "column0": "Kattie",
       "column1": "216-923-3715",
       "column2": "kattie@vonasek.org"
    },
    {
       "column0": "Lilli",
       "column1": "325-631-1560",
       "column2": "lilli@aol.com"
    },
    {
       "column0": "Whitley",
       "column1": "817-526-4408",
       "column2": "whitley.tomasulo@aol.com"
    },
    {
       "column0": "Barbra",
       "column1": "718-201-3751",
       "column2": "badkin@hotmail.com"
    },
    {
       "column0": "Hermila",
       "column1": "401-893-4882",
       "column2": "hermila_thyberg@hotmail.com"
    },
    {
       "column0": "Jesusita",
       "column1": "717-885-9118",
       "column2": "jesusita.flister@hotmail.com"
    },
    {
       "column0": "Caitlin",
       "column1": "401-948-4982",
       "column2": "caitlin.julia@julia.org"
    },
    {
       "column0": "Roosevelt",
       "column1": "305-622-4739",
       "column2": "roosevelt.hoffis@aol.com"
    },
    {
       "column0": "Helaine",
       "column1": "201-832-4168",
       "column2": "hhalter@yahoo.com"
    },
    {
       "column0": "Lorean",
       "column1": "210-856-4979",
       "column2": "lorean.martabano@hotmail.com"
    },
    {
       "column0": "France",
       "column1": "718-478-8504",
       "column2": "france.buzick@yahoo.com"
    },
    {
       "column0": "Justine",
       "column1": "909-993-3242",
       "column2": "jferrario@hotmail.com"
    },
    {
       "column0": "Adelina",
       "column1": "216-230-4892",
       "column2": "adelina_nabours@gmail.com"
    },
    {
       "column0": "Derick",
       "column1": "212-304-4515",
       "column2": "ddhamer@cox.net"
    },
    {
       "column0": "Jerry",
       "column1": "804-762-9576",
       "column2": "jerry.dallen@yahoo.com"
    },
    {
       "column0": "Leota",
       "column1": "706-221-4243",
       "column2": "leota.ragel@gmail.com"
    },
    {
       "column0": "Jutta",
       "column1": "337-515-1438",
       "column2": "jamyot@hotmail.com"
    },
    {
       "column0": "Aja",
       "column1": "973-544-2677",
       "column2": "aja_gehrett@hotmail.com"
    },
    {
       "column0": "Kirk",
       "column1": "607-407-3716",
       "column2": "kirk.herritt@aol.com"
    },
    {
       "column0": "Leonora",
       "column1": "973-412-2995",
       "column2": "leonora@yahoo.com"
    },
    {
       "column0": "Winfred",
       "column1": "208-252-4552",
       "column2": "winfred_brucato@hotmail.com"
    },
    {
       "column0": "Tarra",
       "column1": "415-411-1775",
       "column2": "tarra.nachor@cox.net"
    },
    {
       "column0": "Corinne",
       "column1": "508-942-4186",
       "column2": "corinne@loder.org"
    },
    {
       "column0": "Dulce",
       "column1": "248-357-8718",
       "column2": "dulce_labreche@yahoo.com"
    },
    {
       "column0": "Kate",
       "column1": "920-353-6377",
       "column2": "kate_keneipp@yahoo.com"
    },
    {
       "column0": "Kaitlyn",
       "column1": "410-665-4903",
       "column2": "kaitlyn.ogg@gmail.com"
    },
    {
       "column0": "Sherita",
       "column1": "719-669-1664",
       "column2": "sherita.saras@cox.net"
    },
    {
       "column0": "Lashawnda",
       "column1": "419-588-8719",
       "column2": "lstuer@cox.net"
    },
    {
       "column0": "Ernest",
       "column1": "301-998-9644",
       "column2": "ernest@cox.net"
    },
    {
       "column0": "Nobuko",
       "column1": "508-855-9887",
       "column2": "nobuko.halsey@yahoo.com"
    },
    {
       "column0": "Lavonna",
       "column1": "703-483-1970",
       "column2": "lavonna.wolny@hotmail.com"
    },
    {
       "column0": "Lashaunda",
       "column1": "410-678-2473",
       "column2": "llizama@cox.net"
    },
    {
       "column0": "Mariann",
       "column1": "512-223-4791",
       "column2": "mariann.bilden@aol.com"
    },
    {
       "column0": "Helene",
       "column1": "623-461-8551",
       "column2": "helene@aol.com"
    },
    {
       "column0": "Roselle",
       "column1": "419-571-5920",
       "column2": "roselle.estell@hotmail.com"
    },
    {
       "column0": "Samira",
       "column1": "206-311-4137",
       "column2": "sheintzman@hotmail.com"
    },
    {
       "column0": "Margart",
       "column1": "513-617-2362",
       "column2": "margart_meisel@yahoo.com"
    },
    {
       "column0": "Kristofer",
       "column1": "812-368-1511",
       "column2": "kristofer.bennick@yahoo.com"
    },
    {
       "column0": "Weldon",
       "column1": "847-353-2156",
       "column2": "wacuff@gmail.com"
    },
    {
       "column0": "Shalon",
       "column1": "718-232-2337",
       "column2": "shalon@cox.net"
    },
    {
       "column0": "Denise",
       "column1": "407-446-4358",
       "column2": "denise@patak.org"
    },
    {
       "column0": "Louvenia",
       "column1": "310-820-2117",
       "column2": "louvenia.beech@beech.com"
    },
    {
       "column0": "Audry",
       "column1": "813-797-4816",
       "column2": "audry.yaw@yaw.org"
    },
    {
       "column0": "Kristel",
       "column1": "915-452-1290",
       "column2": "kristel.ehmann@aol.com"
    },
    {
       "column0": "Vincenza",
       "column1": "619-603-5125",
       "column2": "vzepp@gmail.com"
    },
    {
       "column0": "Elouise",
       "column1": "301-841-5012",
       "column2": "egwalthney@yahoo.com"
    },
    {
       "column0": "Venita",
       "column1": "714-523-6653",
       "column2": "venita_maillard@gmail.com"
    },
    {
       "column0": "Kasandra",
       "column1": "314-732-9131",
       "column2": "kasandra_semidey@semidey.com"
    },
    {
       "column0": "Xochitl",
       "column1": "512-233-1831",
       "column2": "xdiscipio@gmail.com"
    },
    {
       "column0": "Maile",
       "column1": "336-670-2640",
       "column2": "mlinahan@yahoo.com"
    },
    {
       "column0": "Krissy",
       "column1": "631-443-4710",
       "column2": "krauser@cox.net"
    },
    {
       "column0": "Pete",
       "column1": "201-825-2514",
       "column2": "pdubaldi@hotmail.com"
    },
    {
       "column0": "Linn",
       "column1": "901-412-4381",
       "column2": "linn_paa@paa.com"
    },
    {
       "column0": "Paris",
       "column1": "404-505-4445",
       "column2": "paris@hotmail.com"
    },
    {
       "column0": "Wynell",
       "column1": "650-473-1262",
       "column2": "wynell_dorshorst@dorshorst.org"
    },
    {
       "column0": "Quentin",
       "column1": "952-702-7993",
       "column2": "qbirkner@aol.com"
    },
    {
       "column0": "Regenia",
       "column1": "480-726-1280",
       "column2": "regenia.kannady@cox.net"
    },
    {
       "column0": "Sheron",
       "column1": "718-976-8610",
       "column2": "sheron@aol.com"
    },
    {
       "column0": "Izetta",
       "column1": "770-844-3447",
       "column2": "izetta.funnell@hotmail.com"
    },
    {
       "column0": "Rodolfo",
       "column1": "507-210-3510",
       "column2": "rodolfo@hotmail.com"
    },
    {
       "column0": "Zona",
       "column1": "203-461-1949",
       "column2": "zona@hotmail.com"
    },
    {
       "column0": "Serina",
       "column1": "260-273-3725",
       "column2": "szagen@aol.com"
    },
    {
       "column0": "Paz",
       "column1": "601-927-8287",
       "column2": "paz_sahagun@cox.net"
    },
    {
       "column0": "Markus",
       "column1": "586-970-7380",
       "column2": "markus@yahoo.com"
    },
    {
       "column0": "Jaclyn",
       "column1": "719-853-3600",
       "column2": "jaclyn@aol.com"
    },
    {
       "column0": "Cyril",
       "column1": "212-745-8484",
       "column2": "cyril_daufeldt@daufeldt.com"
    },
    {
       "column0": "Gayla",
       "column1": "510-686-3407",
       "column2": "gschnitzler@gmail.com"
    },
    {
       "column0": "Erick",
       "column1": "773-704-9903",
       "column2": "erick_nievas@aol.com"
    },
    {
       "column0": "Jennie",
       "column1": "570-218-4831",
       "column2": "jennie@cox.net"
    },
    {
       "column0": "Mitsue",
       "column1": "530-986-9272",
       "column2": "mscipione@scipione.com"
    },
    {
       "column0": "Ciara",
       "column1": "845-823-8877",
       "column2": "cventura@yahoo.com"
    },
    {
       "column0": "Galen",
       "column1": "216-600-6111",
       "column2": "galen@yahoo.com"
    },
    {
       "column0": "Truman",
       "column1": "973-852-2736",
       "column2": "tfeichtner@yahoo.com"
    },
    {
       "column0": "Gail",
       "column1": "907-435-9166",
       "column2": "gail@kitty.com"
    },
    {
       "column0": "Dalene",
       "column1": "215-268-1275",
       "column2": "dalene@schoeneck.org"
    },
    {
       "column0": "Gertude",
       "column1": "513-977-7043",
       "column2": "gertude.witten@gmail.com"
    },
    {
       "column0": "Lizbeth",
       "column1": "310-699-1222",
       "column2": "lizbeth@yahoo.com"
    },
    {
       "column0": "Glenn",
       "column1": "515-370-7348",
       "column2": "gberray@gmail.com"
    },
    {
       "column0": "Lashandra",
       "column1": "610-809-1818",
       "column2": "lashandra@yahoo.com"
    },
    {
       "column0": "Lenna",
       "column1": "919-623-2524",
       "column2": "lnewville@newville.com"
    },
    {
       "column0": "Laurel",
       "column1": "509-695-5199",
       "column2": "laurel@yahoo.com"
    },
    {
       "column0": "Mireya",
       "column1": "914-868-5965",
       "column2": "mireya.frerking@hotmail.com"
    },
    {
       "column0": "Annelle",
       "column1": "410-757-1035",
       "column2": "annelle@yahoo.com"
    },
    {
       "column0": "Dean",
       "column1": "516-847-4418",
       "column2": "dean_ketelsen@gmail.com"
    },
    {
       "column0": "Levi",
       "column1": "508-456-4907",
       "column2": "levi.munis@gmail.com"
    },
    {
       "column0": "Sylvie",
       "column1": "918-644-9555",
       "column2": "sylvie@aol.com"
    },
    {
       "column0": "Sharee",
       "column1": "231-467-9978",
       "column2": "sharee_maile@aol.com"
    },
    {
       "column0": "Cordelia",
       "column1": "337-566-6001",
       "column2": "cordelia_storment@aol.com"
    },
    {
       "column0": "Mollie",
       "column1": "419-975-3182",
       "column2": "mollie_mcdoniel@yahoo.com"
    },
    {
       "column0": "Brett",
       "column1": "619-461-9984",
       "column2": "brett.mccullan@mccullan.com"
    },
    {
       "column0": "Teddy",
       "column1": "203-892-3863",
       "column2": "teddy_pedrozo@aol.com"
    },
    {
       "column0": "Tasia",
       "column1": "201-920-9002",
       "column2": "tasia_andreason@yahoo.com"
    },
    {
       "column0": "Hubert",
       "column1": "330-903-1345",
       "column2": "hubert@walthall.org"
    },
    {
       "column0": "Arthur",
       "column1": "201-238-5688",
       "column2": "arthur.farrow@yahoo.com"
    },
    {
       "column0": "Vilma",
       "column1": "616-737-3085",
       "column2": "vberlanga@berlanga.com"
    },
    {
       "column0": "Billye",
       "column1": "601-567-5386",
       "column2": "billye_miro@cox.net"
    },
    {
       "column0": "Glenna",
       "column1": "901-640-9178",
       "column2": "glenna_slayton@cox.net"
    },
    {
       "column0": "Mitzie",
       "column1": "303-402-1940",
       "column2": "mitzie_hudnall@yahoo.com"
    },
    {
       "column0": "Bernardine",
       "column1": "901-901-4726",
       "column2": "bernardine_rodefer@yahoo.com"
    },
    {
       "column0": "Staci",
       "column1": "626-866-2339",
       "column2": "staci_schmaltz@aol.com"
    },
    {
       "column0": "Nichelle",
       "column1": "773-225-9985",
       "column2": "nichelle_meteer@meteer.com"
    },
    {
       "column0": "Janine",
       "column1": "718-228-5894",
       "column2": "jrhoden@yahoo.com"
    },
    {
       "column0": "Ettie",
       "column1": "509-755-5393",
       "column2": "ettie.hoopengardner@hotmail.com"
    },
    {
       "column0": "Eden",
       "column1": "410-890-7866",
       "column2": "eden_jayson@yahoo.com"
    },
    {
       "column0": "Lynelle",
       "column1": "973-860-8610",
       "column2": "lynelle_auber@gmail.com"
    },
    {
       "column0": "Merissa",
       "column1": "562-579-6900",
       "column2": "merissa.tomblin@gmail.com"
    },
    {
       "column0": "Golda",
       "column1": "732-628-9909",
       "column2": "golda_kaniecki@yahoo.com"
    },
    {
       "column0": "Catarina",
       "column1": "973-210-3994",
       "column2": "catarina_gleich@hotmail.com"
    },
    {
       "column0": "Virgie",
       "column1": "303-776-7548",
       "column2": "vkiel@hotmail.com"
    },
    {
       "column0": "Jolene",
       "column1": "757-682-7116",
       "column2": "jolene@yahoo.com"
    },
    {
       "column0": "Keneth",
       "column1": "602-919-4211",
       "column2": "keneth@yahoo.com"
    },
    {
       "column0": "Rikki",
       "column1": "305-968-9487",
       "column2": "rikki@nayar.com"
    },
    {
       "column0": "Elke",
       "column1": "602-896-2993",
       "column2": "elke_sengbusch@yahoo.com"
    },
    {
       "column0": "Hoa",
       "column1": "386-526-7800",
       "column2": "hoa@sarao.org"
    },
    {
       "column0": "Trinidad",
       "column1": "415-331-9634",
       "column2": "trinidad_mcrae@yahoo.com"
    },
    {
       "column0": "Mari",
       "column1": "858-793-9684",
       "column2": "mari_lueckenbach@yahoo.com"
    },
    {
       "column0": "Selma",
       "column1": "201-991-8369",
       "column2": "selma.husser@cox.net"
    },
    {
       "column0": "Antione",
       "column1": "909-430-7765",
       "column2": "aonofrio@onofrio.com"
    },
    {
       "column0": "Luisa",
       "column1": "617-365-2134",
       "column2": "ljurney@hotmail.com"
    },
    {
       "column0": "Clorinda",
       "column1": "760-291-5497",
       "column2": "clorinda.heimann@hotmail.com"
    },
    {
       "column0": "Dick",
       "column1": "310-510-9713",
       "column2": "dick@yahoo.com"
    },
    {
       "column0": "Ahmed",
       "column1": "717-528-8996",
       "column2": "ahmed.angalich@angalich.com"
    },
    {
       "column0": "Iluminada",
       "column1": "480-293-2882",
       "column2": "iluminada.ohms@yahoo.com"
    },
    {
       "column0": "Joanna",
       "column1": "561-470-4574",
       "column2": "joanna_leinenbach@hotmail.com"
    },
    {
       "column0": "Caprice",
       "column1": "615-246-1824",
       "column2": "caprice@aol.com"
    },
    {
       "column0": "Stephane",
       "column1": "859-717-7638",
       "column2": "stephane_myricks@cox.net"
    },
    {
       "column0": "Quentin",
       "column1": "734-561-6170",
       "column2": "quentin_swayze@yahoo.com"
    },
    {
       "column0": "Annmarie",
       "column1": "936-751-7961",
       "column2": "annmarie_castros@gmail.com"
    },
    {
       "column0": "Shonda",
       "column1": "973-482-2430",
       "column2": "shonda_greenbush@cox.net"
    },
    {
       "column0": "Cecil",
       "column1": "201-693-3967",
       "column2": "clapage@lapage.com"
    },
    {
       "column0": "Jeanice",
       "column1": "305-988-4162",
       "column2": "jeanice.claucherty@yahoo.com"
    },
    {
       "column0": "Josphine",
       "column1": "931-553-9774",
       "column2": "josphine_villanueva@villanueva.com"
    },
    {
       "column0": "Daniel",
       "column1": "714-771-3880",
       "column2": "dperruzza@perruzza.com"
    },
    {
       "column0": "Cassi",
       "column1": "847-633-3216",
       "column2": "cassi.wildfong@aol.com"
    },
    {
       "column0": "Britt",
       "column1": "215-888-3304",
       "column2": "britt@galam.org"
    },
    {
       "column0": "Adell",
       "column1": "973-654-1561",
       "column2": "adell.lipkin@lipkin.com"
    },
    {
       "column0": "Jacqueline",
       "column1": "814-865-8113",
       "column2": "jacqueline.rowling@yahoo.com"
    },
    {
       "column0": "Lonny",
       "column1": "801-293-9853",
       "column2": "lonny_weglarz@gmail.com"
    },
    {
       "column0": "Lonna",
       "column1": "910-922-3672",
       "column2": "lonna_diestel@gmail.com"
    },
    {
       "column0": "Cristal",
       "column1": "213-975-8026",
       "column2": "cristal@cox.net"
    },
    {
       "column0": "Kenneth",
       "column1": "517-499-2322",
       "column2": "kenneth.grenet@grenet.org"
    },
    {
       "column0": "Elli",
       "column1": "315-818-2638",
       "column2": "emclaird@mclaird.com"
    },
    {
       "column0": "Alline",
       "column1": "574-656-2800",
       "column2": "ajeanty@gmail.com"
    },
    {
       "column0": "Sharika",
       "column1": "407-312-1691",
       "column2": "sharika.eanes@aol.com"
    },
    {
       "column0": "Nu",
       "column1": "973-751-9003",
       "column2": "nu@gmail.com"
    },
    {
       "column0": "Daniela",
       "column1": "609-200-8577",
       "column2": "dcomnick@cox.net"
    },
    {
       "column0": "Cecilia",
       "column1": "608-382-4541",
       "column2": "cecilia_colaizzo@colaizzo.com"
    },
    {
       "column0": "Leslie",
       "column1": "914-861-9748",
       "column2": "leslie@cox.net"
    },
    {
       "column0": "Nan",
       "column1": "336-370-5333",
       "column2": "nan@koppinger.com"
    },
    {
       "column0": "Izetta",
       "column1": "410-473-1708",
       "column2": "idewar@dewar.com"
    },
    {
       "column0": "Tegan",
       "column1": "732-730-2692",
       "column2": "tegan.arceo@arceo.org"
    },
    {
       "column0": "Ruthann",
       "column1": "830-258-2769",
       "column2": "ruthann@hotmail.com"
    },
    {
       "column0": "Joni",
       "column1": "847-519-5906",
       "column2": "joni_breland@cox.net"
    },
    {
       "column0": "Vi",
       "column1": "732-605-4781",
       "column2": "vrentfro@cox.net"
    },
    {
       "column0": "Colette",
       "column1": "402-896-5943",
       "column2": "colette.kardas@yahoo.com"
    },
    {
       "column0": "Malcolm",
       "column1": "703-221-5602",
       "column2": "malcolm_tromblay@cox.net"
    },
    {
       "column0": "Ryan",
       "column1": "972-558-1665",
       "column2": "ryan@cox.net"
    },
    {
       "column0": "Jess",
       "column1": "212-510-4633",
       "column2": "jess.chaffins@chaffins.org"
    },
    {
       "column0": "Sharen",
       "column1": "516-816-1541",
       "column2": "sbourbon@yahoo.com"
    },
    {
       "column0": "Nickolas",
       "column1": "352-598-8301",
       "column2": "nickolas_juvera@cox.net"
    },
    {
       "column0": "Gary",
       "column1": "317-542-6023",
       "column2": "gary_nunlee@nunlee.org"
    },
    {
       "column0": "Diane",
       "column1": "816-557-9673",
       "column2": "diane@cox.net"
    },
    {
       "column0": "Roslyn",
       "column1": "601-234-9632",
       "column2": "roslyn.chavous@chavous.org"
    },
    {
       "column0": "Glory",
       "column1": "325-869-2649",
       "column2": "glory@yahoo.com"
    },
    {
       "column0": "Rasheeda",
       "column1": "408-805-4309",
       "column2": "rasheeda@aol.com"
    },
    {
       "column0": "Alpha",
       "column1": "856-312-2629",
       "column2": "alpha@yahoo.com"
    },
    {
       "column0": "Refugia",
       "column1": "510-974-8671",
       "column2": "refugia.jacobos@jacobos.com"
    },
    {
       "column0": "Shawnda",
       "column1": "407-538-5106",
       "column2": "shawnda.yori@yahoo.com"
    },
    {
       "column0": "Mona",
       "column1": "307-403-1488",
       "column2": "mdelasancha@hotmail.com"
    },
    {
       "column0": "Gilma",
       "column1": "516-393-9967",
       "column2": "gilma_liukko@gmail.com"
    },
    {
       "column0": "Janey",
       "column1": "608-967-7194",
       "column2": "jgabisi@hotmail.com"
    },
    {
       "column0": "Lili",
       "column1": "201-431-2989",
       "column2": "lili.paskin@cox.net"
    },
    {
       "column0": "Loren",
       "column1": "570-648-3035",
       "column2": "loren.asar@aol.com"
    },
    {
       "column0": "Dorothy",
       "column1": "858-617-7834",
       "column2": "dorothy@cox.net"
    },
    {
       "column0": "Gail",
       "column1": "760-616-5388",
       "column2": "gail_similton@similton.com"
    },
    {
       "column0": "Catalina",
       "column1": "609-373-3332",
       "column2": "catalina@hotmail.com"
    },
    {
       "column0": "Lawrence",
       "column1": "401-465-6432",
       "column2": "lawrence.lorens@hotmail.com"
    },
    {
       "column0": "Carlee",
       "column1": "785-347-1805",
       "column2": "carlee.boulter@hotmail.com"
    },
    {
       "column0": "Thaddeus",
       "column1": "916-920-3571",
       "column2": "tankeny@ankeny.org"
    },
    {
       "column0": "Jovita",
       "column1": "386-248-4118",
       "column2": "joles@gmail.com"
    },
    {
       "column0": "Alesia",
       "column1": "202-646-7516",
       "column2": "alesia_hixenbaugh@hixenbaugh.org"
    },
    {
       "column0": "Lai",
       "column1": "415-423-3294",
       "column2": "lai@gmail.com"
    },
    {
       "column0": "Brittni",
       "column1": "208-709-1235",
       "column2": "bgillaspie@gillaspie.com"
    },
    {
       "column0": "Raylene",
       "column1": "574-499-1454",
       "column2": "rkampa@kampa.org"
    },
    {
       "column0": "Flo",
       "column1": "308-726-2182",
       "column2": "flo.bookamer@cox.net"
    },
    {
       "column0": "Jani",
       "column1": "206-711-6498",
       "column2": "jbiddy@yahoo.com"
    },
    {
       "column0": "Chauncey",
       "column1": "407-413-4842",
       "column2": "chauncey_motley@aol.com"
    }
   ]
